numiconveri/__init__.py
numiconveri/__main__.py
numiconveri/config.py
numiconveri-0.1.1.dist-info/LICENSE
numiconveri-0.1.1.dist-info/METADATA
numiconveri-0.1.1.dist-info/WHEEL
numiconveri-0.1.1.dist-info/entry_points.txt
numiconveri-0.1.1.dist-info/top_level.txt
numiconveri-0.1.1.dist-info/RECORD
