Metadata-Version: 2.1
Name: numiconveri
Version: 0.1.1
Home-page: https://github.com/PYthonCoder1128/numiconveri
Author: Torrez
Author-email: that1.stinkyarmpits@gmail.com
Classifier: Programming Language :: Python :: 3
Classifier: License :: OSI Approved :: MIT License
Classifier: Operating System :: OS Independent
Requires-Python: >=3.9
License-File: LICENSE
